sphinx_fakeinv.py
sphinx_fakeinv-1.0.0.data/scripts/sphinx_fakeinv.py
sphinx_fakeinv-1.0.0.dist-info/DESCRIPTION.rst
sphinx_fakeinv-1.0.0.dist-info/METADATA
sphinx_fakeinv-1.0.0.dist-info/RECORD
sphinx_fakeinv-1.0.0.dist-info/WHEEL
sphinx_fakeinv-1.0.0.dist-info/entry_points.txt
sphinx_fakeinv-1.0.0.dist-info/metadata.json
sphinx_fakeinv-1.0.0.dist-info/top_level.txt
