Metadata-Version: 2.0
Name: sphinx-fakeinv
Version: 1.0.0
Summary: Generate fake Intersphinx inventory
Home-page: UNKNOWN
Author: Hong Minhee
Author-email: hongminhee@member.fsf.org
License: GPLv3 or later
Keywords: docs sphinx intersphinx
Platform: UNKNOWN
Classifier: Development Status :: 4 - Beta
Classifier: Environment :: Console
Classifier: Framework :: Sphinx
Classifier: Intended Audience :: Developers
Classifier: License :: OSI Approved :: GNU General Public License v3 or later (GPLv3+)
Classifier: Operating System :: OS Independent
Classifier: Programming Language :: Python :: 2.6
Classifier: Programming Language :: Python :: 2.7
Classifier: Programming Language :: Python :: 3.3
Classifier: Programming Language :: Python :: 3.4
Classifier: Programming Language :: Python :: 3.5
Classifier: Programming Language :: Python :: Implementation :: CPython
Classifier: Programming Language :: Python :: Implementation :: PyPy
Classifier: Programming Language :: Python :: Implementation :: Stackless
Classifier: Topic :: Documentation :: Sphinx
Classifier: Topic :: Internet :: WWW/HTTP :: Indexing/Search
Classifier: Topic :: Software Development :: Documentation
Classifier: Topic :: Text Processing :: Indexing
Classifier: Topic :: Utilities
